morse_code_translator/__init__.py
morse_code_translator/dictionary.py
morse_code_translator/enums.py
morse_code_translator/translator.py
morse_code_translator2-1.0.0.dist-info/LICENSE
morse_code_translator2-1.0.0.dist-info/METADATA
morse_code_translator2-1.0.0.dist-info/WHEEL
morse_code_translator2-1.0.0.dist-info/top_level.txt
morse_code_translator2-1.0.0.dist-info/RECORD
