Metadata-Version: 2.1
Name: morse-code-translator2
Version: 1.0.0
Summary: Morse Code Translator
Home-page: https://github.com/yuziaka/morse_code_translator
Author: Yurii Bondarenko
Author-email: ybondarenko.job@gmail.com
License: MIT
Project-URL: Documentation, https://github.com/yuziaka/morse_code_translator
Project-URL: Source Code, https://github.com/yuziaka/morse_code_translator
Platform: UNKNOWN
Classifier: Programming Language :: Python
Classifier: Programming Language :: Python :: 3
Classifier: Programming Language :: Python :: 3.6
Classifier: Programming Language :: Python :: 3.7
Classifier: Programming Language :: Python :: 3.8
Classifier: Programming Language :: Python :: 3.9
Requires-Python: >=3.6.*
License-File: LICENSE
